{"cameraMode":{"drawMode":0,"name":"Shaded","section":"Shading Mode"},"sceneLighting":true,"audioPlay":false,"sceneViewState":{"showFog":true,"showMaterialUpdate":false,"showSkybox":true,"showFlares":true,"showImageEffects":true,"showParticleSystems":true},"in2DMode":false,"pivot":{"x":-6.574141025543213,"y":14.065925598144532,"z":-1.350189208984375},"rotation":{"x":-0.1795511543750763,"y":-0.16964438557624818,"z":0.03145057335495949,"w":-0.9685010313987732},"size":19.67339324951172,"orthographic":false}